{
  "LOCATOR_LOCALE" : [ {
    "$operation" : "CREATE",
    "DT_ATUALIZACAO_NREC" : "30/01/2026 10:33:04",
    "DS_LOCALE" : "pt_BR",
    "NR_SEQ_TIPO_LOCALIZAR" : "26776",
    "NR_SEQUENCIA" : "6883",
    "NM_USUARIO" : "jfperet",
    "NM_USUARIO_NREC" : "jfperet",
    "NM_ATRIBUTO" : "seq",
    "CD_LOCALIZADOR" : "41",
    "CD_LOCALIZADOR_TFL" : "161",
    "DT_ATUALIZACAO" : "30/01/2026 10:33:04"
  } ],
  "TIPO_LOCALIZAR" : [ {
    "$operation" : "MERGE",
    "DS_LOCALIZADOR" : "Test",
    "IE_APRESENTACAO" : "N",
    "TIPO_LOCALIZADOR_CLIENTE" : [ ],
    "NM_USUARIO" : "jfperet",
    "IE_LOCALIZADOR_INTERNO" : "",
    "DT_ATUALIZACAO_NREC" : "30/01/2026 10:32:48",
    "IE_RESTRINGE_ESTAB" : "N",
    "DS_ARVORE" : "treee",
    "NR_SEQUENCIA" : "26776",
    "TIPO_LOCALIZAR_ATRIBUTO" : [ ],
    "DS_SQL" : "select 1 from dual",
    "NM_USUARIO_NREC" : "jfperet",
    "DT_ATUALIZACAO" : "30/01/2026 10:25:43"
  } ],
  "TIPO_LOCALIZAR_ATRIBUTO" : [ {
    "$operation" : "CREATE",
    "IE_TIPO_ATRIBUTO" : "DATE",
    "DS_MASCARA" : "1",
    "IE_OCULTAR_RESTRICAO" : "N",
    "IE_IGNORAR_ACENTUACAO" : "N",
    "IE_GRID" : "N",
    "IE_FOCUS" : "N",
    "NM_ATRIBUTO" : "NR_TEST",
    "CD_EXP_ITEM" : "1",
    "IE_UTILIZA_TARJA_MAGNETICA" : "N",
    "QT_DESLOCAMENTO" : "12",
    "IE_TIPO_RESTRICAO" : "1",
    "IE_RESULTADO" : "N",
    "DT_ATUALIZACAO" : "30/01/2026 10:28:39",
    "IE_DESC_RESULT" : "N",
    "NR_SEQ_GRID" : "12",
    "DS_ITEM" : "Detest",
    "NR_SEQ_TIPO_LOCALIZAR" : "26776",
    "VL_PADRAO" : "1",
    "NM_USUARIO" : "jfperet",
    "QT_TAM_ATRIB_DESC" : "123",
    "DT_ATUALIZACAO_NREC" : "30/01/2026 10:28:39",
    "IE_TIPO_SELECAO" : "",
    "QT_TAM_GRID" : "12",
    "NR_SEQ_APRESENT" : "1",
    "NR_SEQUENCIA" : "40204",
    "DS_SQL" : "SELECT 1 FROM DUAL",
    "NM_USUARIO_NREC" : "jfperet"
  }, {
    "$operation" : "CREATE",
    "IE_TIPO_ATRIBUTO" : "DATE",
    "CD_DOMINIO" : "10682",
    "DS_ITEM" : "test",
    "IE_OCULTAR_RESTRICAO" : "N",
    "NR_SEQ_TIPO_LOCALIZAR" : "26776",
    "IE_IGNORAR_ACENTUACAO" : "N",
    "NM_USUARIO" : "jfperet",
    "IE_GRID" : "N",
    "IE_FOCUS" : "N",
    "NM_ATRIBUTO" : "TEST",
    "CD_EXP_ITEM" : "2",
    "DT_ATUALIZACAO_NREC" : "30/01/2026 10:32:24",
    "IE_TIPO_SELECAO" : "",
    "IE_UTILIZA_TARJA_MAGNETICA" : "N",
    "NR_SEQ_APRESENT" : "1",
    "NR_SEQUENCIA" : "40205",
    "DS_SQL" : "select 1 from dual",
    "IE_TIPO_RESTRICAO" : "1",
    "NM_USUARIO_NREC" : "jfperet",
    "IE_RESULTADO" : "N",
    "DT_ATUALIZACAO" : "30/01/2026 10:32:24",
    "IE_DESC_RESULT" : "N"
  } ]
}